setup.py
toothpick/__init__.py
toothpick/_version.py
toothpick/associations.py
toothpick/base.py
toothpick/cache.py
toothpick/configs.py
toothpick/errors.py
toothpick/exceptions.py
toothpick/hooks.py
toothpick/resources.py
toothpick/validations.py
toothpick/wtforms.py
toothpick.egg-info/PKG-INFO
toothpick.egg-info/SOURCES.txt
toothpick.egg-info/dependency_links.txt
toothpick.egg-info/requires.txt
toothpick.egg-info/top_level.txt
toothpick/concerns/__init__.py
toothpick/concerns/cacheable.py
toothpick/concerns/comparable.py
toothpick/concerns/displayable.py
toothpick/concerns/findable.py
toothpick/concerns/has_attributes.py
toothpick/concerns/has_resources.py
toothpick/concerns/persistable.py
toothpick/concerns/serializable.py
toothpick/concerns/validatable.py